{
  "data" : [
    {
        "id" : 0,
        "treeData":
        {
              "name": "UP",
              "id": 0,
              "children": [
                {
                  "name": "North",
                  "id": 1,
                  "collapsed": "true",
                  "children": [
                    {
                      "name": "District1",
                      "id": 5,
                      "children": [
                        {
                          "name": "Block1",
                          "id": 80
                        },
                        {
                          "name": "Block2",
                          "id": 81
                        },
                        {
                          "name": "Block3",
                          "id": 82
                        },
                        {
                          "name": "Block4",
                          "id": 83
                        }
                      ]
                    },
                    {
                      "name": "District2",
                      "id": 6,
                      "collapsed": "true",
                      "children": [
                        {
                          "name": "Block5",
                          "id": 84
                        },
                        {
                          "name": "Block6",
                          "id": 85
                        },
                        {
                          "name": "Block7",
                          "id":86
                        }
                      ]
                    },
                    {
                      "name": "District3",
                      "id": 7,
                      "collapsed": "true",
                      "children": [
                        {
                          "name": "Block8",
                          "id": 87
                        },
                        {
                          "name": "Block9",
                          "id": 88
                        }
                      ]
                    }
                  ]
                }
              ]
            }

    },

    {
      "id" : 5,
      "treeData":
      {
        "name": "District1",
        "id": 5,
        "children": [
          {
            "name": "Block1",
            "id": 80
          },
          {
            "name": "Block2",
            "id": 81
          },
          {
            "name": "Block3",
            "id": 82
          },
          {
            "name": "Block4",
            "id": 83
          }
        ]
      }
    },

    {
      "id":6,
      "treeData":
      {
        "name": "District2",
        "id": 6,
        "collapsed": true,
        "children": [
          {
            "name": "Block5",
            "id": 84
          },
          {
            "name": "Block6",
            "id": 85
          },
          {
            "name": "Block7",
            "id":86
          }
        ]
      }
    },

    {
      "id":7,
      "treeData":
      {
        "name": "District3",
        "id": 7,
        "collapsed": true,
        "children": [
          {
            "name": "Block8",
            "id": 87
          },
          {
            "name": "Block9",
            "id": 88
          }
        ]
      }
    }

  ]
}
